{"about.md":"f60ee874","algorithm_fibonacci.md":"9e5de339","algorithm_index.md":"d1e7a209","algorithm_josephus-problem.md":"f84cf811","algorithm_permute.md":"0010a8c8","algorithm_sudoku.md":"f252a55f","books.md":"70aa07b5","docs_android.md":"e06876d7","docs_calculator.md":"4623799d","docs_code_zhihu-billboard.md":"3188d9d8","docs_git.md":"971db67d","docs_index.md":"7feffa96","docs_markdown.md":"755d3250","docs_more.md":"aac1fba9","docs_python.md":"0976fedb","docs_what.md":"91001ff8","index.md":"87618a9d","link.md":"1f6028db","public_python_readme.md":"e1d3edf8","python_1.md":"a0660e4f","yhz_books.md":"ac003bcc","yhz_films.md":"9694763b","yhz_gu-shi-wen.md":"9a1f02d9","yhz_help.md":"9c2fbbf4","yhz_index.md":"81798dba","yhz_more.md":"a350e4a5","yhz_read-list-2020.md":"ae32d00a","yhz_unicode.md":"1d5a73e5"}
