{"about.md":"89f7effa","algorithm_fibonacci.md":"eecc9fd1","algorithm_index.md":"40c472ae","algorithm_josephus-problem.md":"9b7d8d16","algorithm_permute.md":"fbf5e7d5","algorithm_sudoku.md":"90170dbb","books.md":"a926ec32","docs_git.md":"3d75f139","docs_index.md":"52718b39","docs_markdown.md":"78dae4af","docs_more.md":"a051a49e","docs_what.md":"b0632ed7","index.md":"782be615","link.md":"3daadc8b","yhz_books.md":"2fe18dbc","yhz_films.md":"e66281f8","yhz_gu-shi-wen.md":"f02944be","yhz_index.md":"358cc83e","yhz_more.md":"1a01212e","yhz_read-list-2020.md":"a83a8977"}
