{"about.md":"127699ad","algorithm_fibonacci.md":"f4b713d8","algorithm_index.md":"ab782019","algorithm_josephus-problem.md":"ddc494d8","algorithm_permute.md":"b33eddc9","algorithm_sudoku.md":"1bb48576","books.md":"4dab1f28","docs_git.md":"f39a342a","docs_index.md":"88fee4a0","docs_markdown.md":"a6733060","docs_more.md":"edc8005d","docs_what.md":"32d6f40d","index.md":"2e6a2535","link.md":"71dff668","yhz_books.md":"d4fe9226","yhz_films.md":"2e4823c3","yhz_gu-shi-wen.md":"7180de39","yhz_help.md":"c982f38e","yhz_index.md":"ca50f608","yhz_more.md":"aa49a4cd","yhz_read-list-2020.md":"d69b68d0"}
