{"about.md":"17694e80","algorithm_fibonacci.md":"f6af9c02","algorithm_index.md":"107cbe8d","algorithm_josephus-problem.md":"c560907f","algorithm_permute.md":"789d9948","algorithm_sudoku.md":"6291705e","books.md":"08321815","docs_code_zhihu-billboard.md":"4e975b5e","docs_git.md":"cab6f0cb","docs_index.md":"94e69da3","docs_markdown.md":"bfe0bd60","docs_more.md":"16687175","docs_python.md":"1a9aa7de","docs_what.md":"f0b128b6","index.md":"63be23d7","link.md":"fbebdee8","python_1.md":"02b2570a","yhz_books.md":"a1c33fe3","yhz_films.md":"bf03d88c","yhz_gu-shi-wen.md":"25f517f5","yhz_help.md":"c2e5ae8b","yhz_index.md":"b3cc29d0","yhz_more.md":"56716dbd","yhz_read-list-2020.md":"206e0ffd","yhz_unicode.md":"10724201"}
